.gitignore
.travis.yml
API.markdown
AUTHORS
CHANGELOG.md
CONTRIBUTING.md
LICENSE
MANIFEST.in
README.markdown
appveyor.yml
setup.cfg
setup.py
.github/issue_template.md
src/pydaab/__init__.py
src/pydaab/audio_segment.py
src/pydaab/effects.py
src/pydaab/exceptions.py
src/pydaab/generators.py
src/pydaab/logging_utils.py
src/pydaab/playback.py
src/pydaab/pyaudioop.py
src/pydaab/scipy_effects.py
src/pydaab/silence.py
src/pydaab/utils.py
src/pydaab.egg-info/PKG-INFO
src/pydaab.egg-info/SOURCES.txt
src/pydaab.egg-info/dependency_links.txt
src/pydaab.egg-info/top_level.txt
test/__init__.py
test/test.py
test/data/bach.ogg
test/data/cover.jpg
test/data/cover.png
test/data/creative_common.mp4
test/data/format_test.m4a
test/data/party.mp3
test/data/tessst.mp3
test/data/test-192khz-16bit.wav
test/data/test-192khz-24bit.wav
test/data/test-192khz-32bit.flac
test/data/test-192khz-32bit.wav
test/data/test-192khz-64bit.wav
test/data/test-dc_offset.wav
test/data/test1-24bit.wav
test/data/test1-8bit.wav
test/data/test1.mp3
test/data/test1.raw
test/data/test1.wav
test/data/test1_empty.wav
test/data/test2.mp3
test/data/test3.mp3
test/data/test4.wav
test/data/test5.webm
test/data/wrong_extension.aac